LICENSE
MANIFEST.in
NOTICE
README.md
fix
setup.py
littlechef/__init__.py
littlechef/chef.py
littlechef/colors.py
littlechef/environment.rb
littlechef/exceptions.py
littlechef/lib.py
littlechef/runner.py
littlechef/solo.py
littlechef/solo.rb.j2
littlechef.egg-info/PKG-INFO
littlechef.egg-info/SOURCES.txt
littlechef.egg-info/dependency_links.txt
littlechef.egg-info/requires.txt
littlechef.egg-info/top_level.txt