Metadata-Version: 1.1
Name: littlechef
Version: 1.8.0
Summary: Cook with Chef without a Chef Server
Home-page: http://github.com/tobami/littlechef
Author: Miquel Torres
Author-email: tobami@gmail.com
License: UNKNOWN
Download-URL: http://github.com/tobami/littlechef/tags
Keywords: chef,devops,operations,sysadmin
Platform: UNKNOWN
Classifier: Programming Language :: Python
Classifier: Development Status :: 5 - Production/Stable 
Classifier: Environment :: Console
Classifier: Intended Audience :: Developers
Classifier: License :: OSI Approved :: Apache Software License
Classifier: Operating System :: OS Independent
Classifier: Topic :: System :: Systems Administration
